<TextureAtlas imagePath="assets/sheet_tanks.png">
    <SubTexture name="barrelBeige.png" x="108" y="842" width="50" height="16"/>
    <SubTexture name="barrelBeige_outline.png" x="368" y="840" width="58" height="24"/>
    <SubTexture name="barrelBlack.png" x="426" y="840" width="50" height="16"/>
    <SubTexture name="barrelBlack_outline.png" x="168" y="818" width="58" height="24"/>
    <SubTexture name="barrelBlue.png" x="58" y="850" width="50" height="16"/>
    <SubTexture name="barrelBlue_outline.png" x="226" y="827" width="58" height="24"/>
    <SubTexture name="barrelGreen.png" x="58" y="834" width="50" height="16"/>
    <SubTexture name="barrelGreen_outline.png" x="110" y="818" width="58" height="24"/>
    <SubTexture name="barrelGreen_side.png" x="48" y="746" width="62" height="44"/>
    <SubTexture name="barrelGreen_side_damaged.png" x="48" y="790" width="62" height="44"/>
    <SubTexture name="barrelGreen_up.png" x="0" y="746" width="48" height="48"/>
    <SubTexture name="barrelGrey_sde_rust.png" x="244" y="783" width="62" height="44"/>
    <SubTexture name="barrelGrey_side.png" x="410" y="796" width="62" height="44"/>
    <SubTexture name="barrelGrey_up.png" x="252" y="735" width="48" height="48"/>
    <SubTexture name="barrelRed.png" x="158" y="842" width="50" height="16"/>
    <SubTexture name="barrelRed_outline.png" x="0" y="834" width="58" height="24"/>
    <SubTexture name="barrelRed_side.png" x="306" y="805" width="62" height="44"/>
    <SubTexture name="barrelRed_up.png" x="454" y="730" width="48" height="48"/>
    <SubTexture name="bulletBeige.png" x="481" y="48" width="26" height="12"/>
    <SubTexture name="bulletBeigeSilver.png" x="345" y="188" width="26" height="12"/>
    <SubTexture name="bulletBeigeSilver_outline.png" x="140" y="671" width="34" height="20"/>
    <SubTexture name="bulletBeige_outline.png" x="345" y="128" width="34" height="20"/>
    <SubTexture name="bulletBlue.png" x="481" y="0" width="26" height="12"/>
    <SubTexture name="bulletBlueSilver.png" x="481" y="12" width="26" height="12"/>
    <SubTexture name="bulletBlueSilver_outline.png" x="345" y="148" width="34" height="20"/>
    <SubTexture name="bulletBlue_outline.png" x="300" y="755" width="34" height="20"/>
    <SubTexture name="bulletGreen.png" x="481" y="24" width="26" height="12"/>
    <SubTexture name="bulletGreenSilver.png" x="481" y="36" width="26" height="12"/>
    <SubTexture name="bulletGreenSilver_outline.png" x="140" y="691" width="34" height="20"/>
    <SubTexture name="bulletGreen_outline.png" x="345" y="168" width="34" height="20"/>
    <SubTexture name="bulletRed.png" x="481" y="120" width="26" height="12"/>
    <SubTexture name="bulletRedSilver.png" x="481" y="60" width="26" height="12"/>
    <SubTexture name="bulletRedSilver_outline.png" x="140" y="711" width="34" height="20"/>
    <SubTexture name="bulletRed_outline.png" x="300" y="735" width="34" height="20"/>
    <SubTexture name="bulletSilver.png" x="481" y="72" width="26" height="12"/>
    <SubTexture name="bulletSilverSilver.png" x="481" y="84" width="26" height="12"/>
    <SubTexture name="bulletSilverSilver_outline.png" x="472" y="778" width="34" height="20"/>
    <SubTexture name="bulletSilver_outline.png" x="306" y="775" width="34" height="20"/>
    <SubTexture name="bulletYellow.png" x="481" y="96" width="26" height="12"/>
    <SubTexture name="bulletYellowSilver.png" x="481" y="108" width="26" height="12"/>
    <SubTexture name="bulletYellowSilver_outline.png" x="0" y="794" width="34" height="20"/>
    <SubTexture name="bulletYellow_outline.png" x="0" y="814" width="34" height="20"/>
    <SubTexture name="dirt.png" x="0" y="0" width="128" height="128"/>
    <SubTexture name="grass.png" x="128" y="0" width="128" height="128"/>
    <SubTexture name="oil.png" x="408" y="200" width="96" height="96"/>
    <SubTexture name="sand.png" x="256" y="0" width="128" height="128"/>
    <SubTexture name="sandbagBeige.png" x="301" y="128" width="44" height="66"/>
    <SubTexture name="sandbagBrown.png" x="410" y="730" width="44" height="66"/>
    <SubTexture name="smokeGrey0.png" x="188" y="416" width="87" height="87"/>
    <SubTexture name="smokeGrey1.png" x="408" y="296" width="89" height="92"/>
    <SubTexture name="smokeGrey2.png" x="384" y="478" width="99" height="90"/>
    <SubTexture name="smokeGrey3.png" x="353" y="651" width="79" height="79"/>
    <SubTexture name="smokeGrey4.png" x="97" y="128" width="97" height="100"/>
    <SubTexture name="smokeGrey5.png" x="194" y="128" width="107" height="98"/>
    <SubTexture name="smokeOrange0.png" x="275" y="486" width="87" height="87"/>
    <SubTexture name="smokeOrange1.png" x="196" y="324" width="89" height="92"/>
    <SubTexture name="smokeOrange2.png" x="408" y="388" width="99" height="90"/>
    <SubTexture name="smokeOrange3.png" x="261" y="656" width="79" height="79"/>
    <SubTexture name="smokeOrange4.png" x="384" y="0" width="97" height="100"/>
    <SubTexture name="smokeOrange5.png" x="0" y="228" width="107" height="98"/>
    <SubTexture name="smokeWhite0.png" x="107" y="324" width="89" height="92"/>
    <SubTexture name="smokeWhite1.png" x="285" y="396" width="99" height="90"/>
    <SubTexture name="smokeWhite2.png" x="182" y="590" width="79" height="79"/>
    <SubTexture name="smokeWhite3.png" x="0" y="128" width="97" height="100"/>
    <SubTexture name="smokeWhite4.png" x="194" y="226" width="107" height="98"/>
    <SubTexture name="smokeWhite5.png" x="0" y="418" width="87" height="87"/>
    <SubTexture name="smokeYellow0.png" x="107" y="228" width="87" height="87"/>
    <SubTexture name="smokeYellow1.png" x="0" y="326" width="89" height="92"/>
    <SubTexture name="smokeYellow2.png" x="89" y="416" width="99" height="90"/>
    <SubTexture name="smokeYellow3.png" x="432" y="651" width="79" height="79"/>
    <SubTexture name="smokeYellow4.png" x="384" y="100" width="97" height="100"/>
    <SubTexture name="smokeYellow5.png" x="301" y="298" width="107" height="98"/>
    <SubTexture name="tankBeige.png" x="340" y="730" width="70" height="75"/>
    <SubTexture name="tankBeige_outline.png" x="0" y="505" width="78" height="83"/>
    <SubTexture name="tankBlack.png" x="0" y="671" width="70" height="75"/>
    <SubTexture name="tankBlack_outline.png" x="362" y="568" width="78" height="83"/>
    <SubTexture name="tankBlue.png" x="70" y="671" width="70" height="75"/>
    <SubTexture name="tankBlue_outline.png" x="78" y="506" width="78" height="83"/>
    <SubTexture name="tankGreen.png" x="182" y="669" width="70" height="75"/>
    <SubTexture name="tankGreen_outline.png" x="275" y="573" width="78" height="83"/>
    <SubTexture name="tankRed.png" x="440" y="568" width="70" height="75"/>
    <SubTexture name="tankRed_outline.png" x="0" y="588" width="78" height="83"/>
    <SubTexture name="tracksLarge.png" x="78" y="589" width="104" height="82"/>
    <SubTexture name="tracksSmall.png" x="140" y="744" width="104" height="74"/>
    <SubTexture name="treeLarge.png" x="301" y="200" width="107" height="98"/>
    <SubTexture name="treeSmall.png" x="188" y="503" width="87" height="87"/>
</TextureAtlas>
